textualize_see/__init__.py
textualize_see/cli.py
textualize_see/errors.py
textualize_see/file_map.py
textualize_see-0.1.1.dist-info/LICENSE
textualize_see-0.1.1.dist-info/METADATA
textualize_see-0.1.1.dist-info/WHEEL
textualize_see-0.1.1.dist-info/entry_points.txt
textualize_see-0.1.1.dist-info/RECORD
