Metadata-Version: 2.1
Name: textualize-see
Version: 0.1.1
Summary: Open files in the terminal
License: MIT
Author: Will McGugan
Author-email: will@textualize.io
Requires-Python: >=3.8,<4.0
Classifier: License :: OSI Approved :: MIT License
Classifier: Programming Language :: Python :: 3
Classifier: Programming Language :: Python :: 3.8
Classifier: Programming Language :: Python :: 3.9
Classifier: Programming Language :: Python :: 3.10
Classifier: Programming Language :: Python :: 3.11
Requires-Dist: click (>=8.1.3,<9.0.0)
Requires-Dist: toml (>=0.10.2,<0.11.0)
